googlefonts_markup/__init__.py
googlefonts_markup/models.py
googlefonts_markup/shortcuts.py
googlefonts_markup-0.4.0.dist-info/LICENSE
googlefonts_markup-0.4.0.dist-info/WHEEL
googlefonts_markup-0.4.0.dist-info/METADATA
googlefonts_markup-0.4.0.dist-info/RECORD
